Metadata-Version: 2.1
Name: oakschool
Version: 0.1
Summary: OOP Learning Example by Oakzkin
Home-page: https://github.com/oakzkin/oakschool
Author: Oakzkin
Author-email: r.intouchpong@gmail.com
License: MIT
Download-URL: https://github.com/oakzkin/oakschool/archive/v_01.tar.gz
Keywords: OOP,Learning,Beginner
Platform: UNKNOWN
Classifier: Development Status :: 3 - Alpha
Classifier: Intended Audience :: Developers
Classifier: Topic :: Software Development :: Build Tools
Classifier: License :: OSI Approved :: MIT License
Classifier: Programming Language :: Python :: 3
Classifier: Programming Language :: Python :: 3.4
Classifier: Programming Language :: Python :: 3.5
Classifier: Programming Language :: Python :: 3.6
Classifier: Programming Language :: Python :: 3.7
Classifier: Programming Language :: Python :: 3.8
Classifier: Programming Language :: Python :: 3.9
